mitake/__init__.py
mitake/client.py
mitake/exceptions.py
mitake-0.9.2.dist-info/licenses/LICENSE
tests/__init__.py
tests/test_client.py
tests/test_encoding.py
tests/test_mitake_complete.py
tests/test_sms.py
mitake-0.9.2.dist-info/METADATA
mitake-0.9.2.dist-info/WHEEL
mitake-0.9.2.dist-info/top_level.txt
mitake-0.9.2.dist-info/RECORD
