Metadata-Version: 2.4
Name: mitake
Version: 0.9.2
Summary: Python library for Mitake SMS API
Home-page: https://github.com/tzangms/mitake
Author: tzangms
Author-email: tzangms@gmail.com
Project-URL: Bug Reports, https://github.com/tzangms/mitake/issues
Project-URL: Source, https://github.com/tzangms/mitake
Keywords: mitake sms api taiwan
Classifier: Development Status :: 3 - Alpha
Classifier: Intended Audience :: Developers
Classifier: License :: OSI Approved :: MIT License
Classifier: Operating System :: OS Independent
Classifier: Programming Language :: Python :: 3
Classifier: Programming Language :: Python :: 3.8
Classifier: Programming Language :: Python :: 3.9
Classifier: Programming Language :: Python :: 3.10
Classifier: Programming Language :: Python :: 3.11
Requires-Python: >=3.8
License-File: LICENSE
Requires-Dist: requests>=2.25.0
Dynamic: author
Dynamic: author-email
Dynamic: classifier
Dynamic: description
Dynamic: description-content-type
Dynamic: home-page
Dynamic: keywords
Dynamic: license-file
Dynamic: project-url
Dynamic: requires-dist
Dynamic: requires-python
Dynamic: summary
